harica/__init__.py
harica/harica_client.py
harica/main.py
harica/utils.py
harica-0.2.1.dist-info/LICENSE.md
harica-0.2.1.dist-info/METADATA
harica-0.2.1.dist-info/WHEEL
harica-0.2.1.dist-info/entry_points.txt
harica-0.2.1.dist-info/RECORD
